LICENSE
README.rst
pyproject.toml
setup.py
tnotify/__init__.py
tnotify/bot.py
tnotify/logger.py
tnotify/misc.py
tnotify.egg-info/PKG-INFO
tnotify.egg-info/SOURCES.txt
tnotify.egg-info/dependency_links.txt
tnotify.egg-info/requires.txt
tnotify.egg-info/top_level.txt